{
	"jsonversion":		"2023.04.13",
	"changeLog":	[
						"2023.04.13 : New version with Get-NameAndProduct.ps1 called separately in Base TS"
					],
	"entries":	[
		{
			"computernamestring": 	"all",
			"script":	"scripts\\Set-ReloadMode.ps1",
			"argumentlist":		""
		},
		{
			"computernamestring": 	"all",
			"script":	"scripts\\Find-Disk.ps1",
			"argumentlist":		""
		},
		{
			"computernamestring": 	"all",
			"script":	"scripts\\Get-BIOS-Settings.ps1",
			"argumentlist":		""
		},
        {
			"computernamestring": 	"all",
			"script":	"scripts\\Show-Win11ProductSummary.ps1",
			"argumentlist":		""
		}
	]
}
